milkshakelang/__init__.py
milkshakelang/__main__.py
milkshakelang/interpreter.py
milkshakelang/milkshake.py
milkshakelang/utils.py
milkshakelang-0.1.0.dist-info/LICENSE
milkshakelang-0.1.0.dist-info/METADATA
milkshakelang-0.1.0.dist-info/WHEEL
milkshakelang-0.1.0.dist-info/entry_points.txt
milkshakelang-0.1.0.dist-info/top_level.txt
milkshakelang-0.1.0.dist-info/RECORD
