Metadata-Version: 2.1
Name: milkshakelang
Version: 0.1.0
Summary: The MilkShake Programming Language.
Home-page: https://github.com/dayyass/milkshakelang
Author: Dani El-Ayyass
Author-email: dayyass@yandex.ru
License: UNKNOWN
Platform: UNKNOWN
